visdetect/analysis.py
visdetect/config.py
visdetect/metrics.py
visdetect/plots.py
visdetect/run_analysis.py
visdetect/run_show.py
visdetect/helpers/__init__.py
visdetect/helpers/dataset_coco_format.py
visdetect/helpers/dataset_kensho_format.py
visdetect-0.0.3.data/scripts/visdetect
visdetect-0.0.3.dist-info/METADATA
visdetect-0.0.3.dist-info/WHEEL
visdetect-0.0.3.dist-info/top_level.txt
visdetect-0.0.3.dist-info/RECORD
